delicate/__init__.py
delicate/messages.py
delicate-1.0.2.dist-info/LICENSE
delicate-1.0.2.dist-info/METADATA
delicate-1.0.2.dist-info/WHEEL
delicate-1.0.2.dist-info/top_level.txt
delicate-1.0.2.dist-info/RECORD
