Metadata-Version: 2.1
Name: delicate
Version: 1.0.2
Summary: Printing colored messages to the CLI
Home-page: https://github.com/adventgroup/delicate
Author: Advent Group
Author-email: development@adventgroup.net
License: UNKNOWN
Platform: UNKNOWN
Requires-Python: >=3.6
License-File: LICENSE
